duty-1.7.2.dist-info/METADATA
duty-1.7.2.dist-info/WHEEL
duty-1.7.2.dist-info/entry_points.txt
duty-1.7.2.dist-info/licenses/LICENSE
duty/__init__.py
duty/__main__.py
duty/_internal/__init__.py
duty/_internal/callables/__init__.py
duty/_internal/callables/_io.py
duty/_internal/callables/autoflake.py
duty/_internal/callables/black.py
duty/_internal/callables/blacken_docs.py
duty/_internal/callables/build.py
duty/_internal/callables/coverage.py
duty/_internal/callables/flake8.py
duty/_internal/callables/git_changelog.py
duty/_internal/callables/griffe.py
duty/_internal/callables/interrogate.py
duty/_internal/callables/isort.py
duty/_internal/callables/mkdocs.py
duty/_internal/callables/mypy.py
duty/_internal/callables/pytest.py
duty/_internal/callables/ruff.py
duty/_internal/callables/safety.py
duty/_internal/callables/ssort.py
duty/_internal/callables/twine.py
duty/_internal/cli.py
duty/_internal/collection.py
duty/_internal/context.py
duty/_internal/debug.py
duty/_internal/decorator.py
duty/_internal/exceptions.py
duty/_internal/tools/__init__.py
duty/_internal/tools/_autoflake.py
duty/_internal/tools/_base.py
duty/_internal/tools/_black.py
duty/_internal/tools/_blacken_docs.py
duty/_internal/tools/_build.py
duty/_internal/tools/_coverage.py
duty/_internal/tools/_flake8.py
duty/_internal/tools/_git_changelog.py
duty/_internal/tools/_griffe.py
duty/_internal/tools/_interrogate.py
duty/_internal/tools/_isort.py
duty/_internal/tools/_mkdocs.py
duty/_internal/tools/_mypy.py
duty/_internal/tools/_pytest.py
duty/_internal/tools/_ruff.py
duty/_internal/tools/_safety.py
duty/_internal/tools/_ssort.py
duty/_internal/tools/_twine.py
duty/_internal/tools/_ty.py
duty/_internal/tools/_yore.py
duty/_internal/validation.py
duty/callables/__init__.py
duty/callables/autoflake.py
duty/callables/black.py
duty/callables/blacken_docs.py
duty/callables/build.py
duty/callables/coverage.py
duty/callables/flake8.py
duty/callables/git_changelog.py
duty/callables/griffe.py
duty/callables/interrogate.py
duty/callables/isort.py
duty/callables/mkdocs.py
duty/callables/mypy.py
duty/callables/pytest.py
duty/callables/ruff.py
duty-1.7.2.dist-info/RECORD
