Metadata-Version: 2.4
Name: duty
Version: 1.7.2
Summary: A simple task runner.
Keywords: task-runner,task,runner,cross-platform
Author-Email: =?utf-8?q?Timoth=C3=A9e_Mazzucotelli?= <dev@pawamoy.fr>
License-Expression: ISC
License-File: LICENSE
Classifier: Development Status :: 4 - Beta
Classifier: Intended Audience :: Developers
Classifier: Programming Language :: Python
Classifier: Programming Language :: Python :: 3
Classifier: Programming Language :: Python :: 3 :: Only
Classifier: Programming Language :: Python :: 3.10
Classifier: Programming Language :: Python :: 3.11
Classifier: Programming Language :: Python :: 3.12
Classifier: Programming Language :: Python :: 3.13
Classifier: Programming Language :: Python :: 3.14
Classifier: Topic :: Documentation
Classifier: Topic :: Software Development
Classifier: Topic :: Utilities
Classifier: Typing :: Typed
Project-URL: Homepage, https://pawamoy.github.io/duty
Project-URL: Documentation, https://pawamoy.github.io/duty
Project-URL: Changelog, https://pawamoy.github.io/duty/changelog
Project-URL: Repository, https://github.com/pawamoy/duty
Project-URL: Issues, https://github.com/pawamoy/duty/issues
Project-URL: Discussions, https://github.com/pawamoy/duty/discussions
Project-URL: Gitter, https://gitter.im/duty/community
Project-URL: Funding, https://github.com/sponsors/pawamoy
Requires-Python: >=3.10
Requires-Dist: failprint>=1.0.5
Requires-Dist: typing-extensions>=4.0; python_version < "3.11"
